bbmuse/__init__.py
bbmuse/example.py
bbmuse-0.0.1.dist-info/licenses/LICENSE
bbmuse-0.0.1.dist-info/METADATA
bbmuse-0.0.1.dist-info/WHEEL
bbmuse-0.0.1.dist-info/top_level.txt
bbmuse-0.0.1.dist-info/RECORD
