Metadata-Version: 2.4
Name: bbmuse
Version: 0.0.1
Summary: The bbmuse project - blackboard system for realtime AI music generation
Author-email: Fabian Ostermann <fabian.ostermann@tu-dortmund.de>
License-Expression: MIT
Project-URL: Homepage, https://github.com/fabianostermann/bbmuse
Project-URL: Issues, https://github.com/fabianostermann/bbmuse/issues
Classifier: Programming Language :: Python :: 3
Classifier: Operating System :: OS Independent
Requires-Python: >=3.9
License-File: LICENSE
Dynamic: license-file
